aliyunsdkecd/__init__.py
aliyunsdkecd/endpoint.py
aliyunsdkecd/request/__init__.py
aliyunsdkecd/request/v20200930/ActivateOfficeSiteRequest.py
aliyunsdkecd/request/v20200930/AddDevicesRequest.py
aliyunsdkecd/request/v20200930/AddUserToDesktopGroupRequest.py
aliyunsdkecd/request/v20200930/ApplyAutoSnapshotPolicyRequest.py
aliyunsdkecd/request/v20200930/ApplyCoordinatePrivilegeRequest.py
aliyunsdkecd/request/v20200930/ApplyCoordinationForMonitoringRequest.py
aliyunsdkecd/request/v20200930/ApproveFotaUpdateRequest.py
aliyunsdkecd/request/v20200930/AssociateNetworkPackageRequest.py
aliyunsdkecd/request/v20200930/AttachCenRequest.py
aliyunsdkecd/request/v20200930/AttachEndUserRequest.py
aliyunsdkecd/request/v20200930/CancelAutoSnapshotPolicyRequest.py
aliyunsdkecd/request/v20200930/CancelCoordinationForMonitoringRequest.py
aliyunsdkecd/request/v20200930/CancelCopyImageRequest.py
aliyunsdkecd/request/v20200930/ClonePolicyGroupRequest.py
aliyunsdkecd/request/v20200930/ConfigADConnectorTrustRequest.py
aliyunsdkecd/request/v20200930/ConfigADConnectorUserRequest.py
aliyunsdkecd/request/v20200930/CopyImageRequest.py
aliyunsdkecd/request/v20200930/CreateADConnectorDirectoryRequest.py
aliyunsdkecd/request/v20200930/CreateADConnectorOfficeSiteRequest.py
aliyunsdkecd/request/v20200930/CreateAndBindNasFileSystemRequest.py
aliyunsdkecd/request/v20200930/CreateAutoSnapshotPolicyRequest.py
aliyunsdkecd/request/v20200930/CreateBundleRequest.py
aliyunsdkecd/request/v20200930/CreateDesktopGroupRequest.py
aliyunsdkecd/request/v20200930/CreateDesktopsRequest.py
aliyunsdkecd/request/v20200930/CreateDiskEncryptionServiceRequest.py
aliyunsdkecd/request/v20200930/CreateImageRequest.py
aliyunsdkecd/request/v20200930/CreateNASFileSystemRequest.py
aliyunsdkecd/request/v20200930/CreateNetworkPackageRequest.py
aliyunsdkecd/request/v20200930/CreatePolicyGroupRequest.py
aliyunsdkecd/request/v20200930/CreateRAMDirectoryRequest.py
aliyunsdkecd/request/v20200930/CreateSimpleOfficeSiteRequest.py
aliyun_python_sdk_ecd-1.0.2.dist-info/LICENSE
aliyun_python_sdk_ecd-1.0.2.dist-info/METADATA
aliyun_python_sdk_ecd-1.0.2.dist-info/WHEEL
aliyun_python_sdk_ecd-1.0.2.dist-info/top_level.txt
aliyun_python_sdk_ecd-1.0.2.dist-info/RECORD
